{"cameraMode":{"drawMode":0,"name":"Shaded","section":"Shading Mode"},"sceneLighting":true,"audioPlay":false,"sceneViewState":{"m_AlwaysRefresh":false,"showFog":true,"showSkybox":true,"showFlares":true,"showImageEffects":true,"showParticleSystems":true,"showVisualEffectGraphs":true,"m_FxEnabled":true},"in2DMode":false,"pivot":{"x":-0.3271470069885254,"y":3.376443862915039,"z":-1.411543846130371},"rotation":{"x":-0.037331532686948779,"y":0.9172962307929993,"z":-0.08861865848302841,"w":-0.38642075657844546},"size":8.10690689086914,"orthographic":false}